ev3_dc/__init__.py
ev3_dc/color.py
ev3_dc/constants.py
ev3_dc/ev3.py
ev3_dc/exceptions.py
ev3_dc/file.py
ev3_dc/functions.py
ev3_dc/gyro.py
ev3_dc/infrared.py
ev3_dc/motor.py
ev3_dc/sound.py
ev3_dc/touch.py
ev3_dc/ultrasonic.py
ev3_dc/vehicle.py
ev3_dc-0.9.10.2.dist-info/LICENSE
ev3_dc-0.9.10.2.dist-info/METADATA
ev3_dc-0.9.10.2.dist-info/WHEEL
ev3_dc-0.9.10.2.dist-info/top_level.txt
ev3_dc-0.9.10.2.dist-info/RECORD
