Metadata-Version: 2.1
Name: ev3-dc
Version: 0.9.10.2
Summary: EV3 direct commands
Home-page: https://github.com/ChristophGaukel/ev3-python3
Author: Christoph Gaukel
Author-email: christoph.gaukel@gmx.de
Classifier: Programming Language :: Python :: 3
Classifier: License :: OSI Approved :: GNU General Public License v3 or later (GPLv3+)
Classifier: Operating System :: OS Independent
Requires-Python: >=3.3
License-File: LICENSE
Requires-Dist: gTTS
Requires-Dist: pyusb
Requires-Dist: thread-task >=0.9.7
